weeknotebot/__init__.py
weeknotebot/cli.py
weeknotebot/config_manager.py
weeknotebot/generator.py
weeknotebot/sources/__init__.py
weeknotebot/sources/anilist_stats.py
weeknotebot/sources/feed.py
weeknotebot/sources/fix_links.py
weeknotebot/sources/goodreads_shelf.py
weeknotebot/sources/text_api.py
weeknotebot-1.9.0.dist-info/METADATA
weeknotebot-1.9.0.dist-info/WHEEL
weeknotebot-1.9.0.dist-info/entry_points.txt
weeknotebot-1.9.0.dist-info/RECORD
