Metadata-Version: 2.4
Name: WeeknoteBot
Version: 1.9.0
Summary: A bot for generate WeekNote for Hugo
Author-email: Fundor333 <github@fundor333.com>
Requires-Python: >=3.10
Requires-Dist: click<9.0.0,>=8.1.8
Requires-Dist: feedparser<7.0.0,>=6.0.11
Requires-Dist: marshmallow<4.0.0,>=3.26.1
Requires-Dist: requests<3.0.0,>=2.32.3
Requires-Dist: rich<14.0.0,>=13.9.4
